[null,{"name":"steamcombo","permissions":"NONE","restriction":"3","actions":[{"channel":"1","varName":"","file":"resources/steam.txt","message":"Your steam combo :D","name":"Send File"},{"title":"RESTOCK","author":"Bamekai","color":"#FF0000","timestamp":"false","url":"http://bamekai.pandalist.tk","authorIcon":"https://yt3.ggpht.com/a/AGF-l7_H-uKfEMclLC2KHncmBVBqWY65qI_m1yWZGA=s48-c-k-c0xffffffff-no-rj-mo","imageUrl":"","thumbUrl":"","storage":"3","varName":"msg","name":"Create Embed Message"},{"channel":"1","varName":"","message":"See last restock :","storage":"0","varName2":"","name":"Send Message"},{"storage":"3","varName":"msg","channel":"1","varName2":"","name":"Send Embed Message"}]},{"name":"origincombo","permissions":"NONE","restriction":"3","actions":[{"channel":"1","varName":"","file":"resources/origin.txt","message":"Your origin combo :D","name":"Send File"},{"title":"RESTOCK","author":"Bamekai","color":"#FF0000","timestamp":"false","url":"http://bamekai.pandalist.tk/","authorIcon":"https://yt3.ggpht.com/a/AGF-l7_H-uKfEMclLC2KHncmBVBqWY65qI_m1yWZGA=s48-c-k-c0xffffffff-no-rj-mo","imageUrl":"","thumbUrl":"","storage":"3","varName":"MSG2","name":"Create Embed Message"},{"channel":"1","varName":"","message":"See last restock :","storage":"0","varName2":"","name":"Send Message"},{"storage":"3","varName":"MSG2","channel":"1","varName2":"","name":"Send Embed Message"}]},{"name":"help","permissions":"NONE","restriction":"0","actions":[{"channel":"0","varName":"","message":"========================\nIn DM send :\n------------------------\n/steamcombo\nGenerate steam combo.\n------------------------\n/origincombo\nGenerate origin combo.\n========================","storage":"0","varName2":"","name":"Send Message"}]},{"name":"setup","permissions":"NONE","restriction":"4","actions":[{"gameName":"Made by Bamekai","gameLink":"","name":"Set Bot Game"},{"username":"Bamekai Combo","name":"Set Bot Username"}]},{"name":"stop","permissions":"NONE","restriction":"1","actions":[{"status":"3","name":"Set Bot Status"}]},{"name":"start","permissions":"NONE","restriction":"1","actions":[{"status":"0","name":"Set Bot Status"}]}]